escafil/__init__.py
escafil-0.0.3.dist-info/DESCRIPTION.rst
escafil-0.0.3.dist-info/METADATA
escafil-0.0.3.dist-info/RECORD
escafil-0.0.3.dist-info/WHEEL
escafil-0.0.3.dist-info/metadata.json
escafil-0.0.3.dist-info/top_level.txt
