Metadata-Version: 2.0
Name: escafil
Version: 0.0.3
Summary: A minimal Kubernetes API client
Home-page: https://github.com/vreon/escafil
Author: Jesse Dubay
Author-email: jesse@jessedubay.com
License: UNKNOWN
Keywords: kubernetes
Platform: UNKNOWN
Classifier: Development Status :: 2 - Pre-Alpha
Classifier: Intended Audience :: Developers
Classifier: License :: OSI Approved :: Apache Software License
Classifier: Programming Language :: Python :: 3
Classifier: Programming Language :: Python :: 3.5
Requires-Dist: requests (>=2,<3)
